track17/__init__.py
track17/admin.py
track17/apps.py
track17/client.py
track17/constants.py
track17/entity.py
track17/exceptions.py
track17/models.py
track17/services.py
track17/settings.py
track17/track17.py
track17/utils.py
track17/validators.py
track17/management/__init__.py
track17/management/commands/__init__.py
track17/management/commands/populate_carriers.py
track17/management/commands/populate_countries.py
track17/migrations/0001_initial.py
track17/migrations/__init__.py
django_ok_17track-0.0.4.dist-info/LICENSE
django_ok_17track-0.0.4.dist-info/METADATA
django_ok_17track-0.0.4.dist-info/WHEEL
django_ok_17track-0.0.4.dist-info/top_level.txt
django_ok_17track-0.0.4.dist-info/RECORD
