Metadata-Version: 2.1
Name: django-ok-17track
Version: 0.0.4
Summary: django-17track is an unofficial 17track.com API wrapper for Django.
Home-page: https://github.com/LowerDeez/django-ok-17track
Author: Oleg Kleschunov
Author-email: igorkleschunov@gmail.com
License: MIT
Keywords: python3,tracking,17track,django
Platform: UNKNOWN
Classifier: Development Status :: 4 - Beta
Classifier: Environment :: Web Environment
Classifier: Intended Audience :: Developers
Classifier: License :: OSI Approved :: MIT License
Classifier: Operating System :: OS Independent
Classifier: Programming Language :: Python :: 3.7
Classifier: Programming Language :: Python :: 3.8
Classifier: Framework :: Django
Classifier: Framework :: Django :: 2.1
Classifier: Framework :: Django :: 2.2
Requires-Dist: django (>=2.1)
Requires-Dist: six
Requires-Dist: mock
